README
setup.py
FastGeo/__init__.py
FastGeo/geo.py
FastGeo/parsers.py
FastGeo.egg-info/PKG-INFO
FastGeo.egg-info/SOURCES.txt
FastGeo.egg-info/dependency_links.txt
FastGeo.egg-info/requires.txt
FastGeo.egg-info/top_level.txt
FastGeo/data/geoip.csv
tests/__init__.py
tests/memory_test.py
tests/time_test.py