Metadata-Version: 1.1
Name: FastGeo
Version: 0.1.2
Summary: A fast, in-memory GeoIP data lookup module
Home-page: https://github.com/theanti9/FastGeo
Author: Ryan Merl
Author-email: ryan@ryanmerl.com
License: MIT
Download-URL: https://github.com/theanti9/FastGeo/releases/download/v0.1.2-alpha/FastGeo-0.1.2-py2.7.egg
Keywords: geo geoip lookup db
Platform: Any
Classifier: Development Status :: 3 - Alpha
Classifier: Intended Audience :: Developers
Classifier: Programming Language :: Python
Classifier: License :: OSI Approved :: MIT License
Classifier: Topic :: Database
Classifier: Topic :: Internet
Classifier: Topic :: Software Development :: Libraries
